Workbook

Sheet Logical Function
A1: Name | B1: Sub 1 | C1: Sub 2 | D1: Sub 3 | E1: Sub 4 | F1: Sub 5 | G1: Total | H1: Average | I1: Max | J1: Min | K1: Count | L1: if | M1: Garde (Nested If) | N1: IFS | O1: And | P1: Or | Q1: Rank
A2: Name 8 | B2: 78 | C2: 45 | D2: 56 | E2: 45 | F2: 90 | G2: =SUM(B2:F2) -> 314 | H2: =AVERAGE(B2:F2) -> 62.8 | I2: =MAX(B2:F2) -> 90 | J2: =MIN(B2:F2) -> 45 | K2: =COUNT(B2:F2) -> 5 | L2: =IF(H2>35,"Pass","Fail") -> Pass | M2: =IF(H2>60,"A",IF(H2>50,"B",IF(H2>40,"C",IF(H2>35,"D","Fail")))) -> A | N2: {=_xlfn.IFS(H2>60,"A",H2>50,"B",H2>40,"C",H2>=35,"D",H2<35,"Fail")} -> A | O2: {=IF(AND(B2:F2>35),"Pass","Fail")} -> Pass | P2: {=IF(OR(B2:F2>35),"Pass","Fail")} -> Pass | Q2: =RANK(H2,$H$2:$H$10,0) -> 3 | Z2: Count | AA2: =COUNT(T2:X9) -> 1
A3: Name 1 | B3: 90 | C3: 54 | D3: 79 | E3: 62 | F3: 87 | G3: =SUM(B3:F3) -> 372 | H3: =AVERAGE(B3:F3) -> 74.4 | I3: =MAX(B3:F3) -> 90 | J3: =MIN(B3:F3) -> 54 | K3: =COUNT(B3:F3) -> 5 | L3: =IF(H3>35,"Pass","Fail") -> Pass | M3: =IF(H3>60,"A",IF(H3>50,"B",IF(H3>40,"C",IF(H3>35,"D","Fail")))) -> A | N3: {=_xlfn.IFS(H3>60,"A",H3>50,"B",H3>40,"C",H3>=35,"D",H3<35,"Fail")} -> A | O3: {=IF(AND(B3:F3>35),"Pass","Fail")} -> Pass | P3: {=IF(OR(B3:F3>35),"Pass","Fail")} -> Pass | Q3: =RANK(H3,$H$2:$H$10,0) -> 1 | Z3: CountA | AA3: =COUNTA(T2:X9) -> 3
A4: Name 5 | B4: 94 | C4: 35 | D4: 55 | E4: 65 | F4: 86 | G4: =SUM(B4:F4) -> 335 | H4: =AVERAGE(B4:F4) -> 67 | I4: =MAX(B4:F4) -> 94 | J4: =MIN(B4:F4) -> 35 | K4: =COUNT(B4:F4) -> 5 | L4: =IF(H4>35,"Pass","Fail") -> Pass | M4: =IF(H4>60,"A",IF(H4>50,"B",IF(H4>40,"C",IF(H4>35,"D","Fail")))) -> A | N4: {=_xlfn.IFS(H4>60,"A",H4>50,"B",H4>40,"C",H4>=35,"D",H4<35,"Fail")} -> A | O4: {=IF(AND(B4:F4>35),"Pass","Fail")} -> Fail | P4: {=IF(OR(B4:F4>35),"Pass","Fail")} -> Pass | Q4: =RANK(H4,$H$2:$H$10,0) -> 2 | T4: A | Z4: CountBlank | AA4: =COUNTBLANK(T2:X9) -> 37
A5: Name 3 | B5: 86 | C5: 56 | D5: 90 | E5: 47 | F5: 14 | G5: =SUM(B5:F5) -> 293 | H5: =AVERAGE(B5:F5) -> 58.6 | I5: =MAX(B5:F5) -> 90 | J5: =MIN(B5:F5) -> 14 | K5: =COUNT(B5:F5) -> 5 | L5: =IF(H5>35,"Pass","Fail") -> Pass | M5: =IF(H5>60,"A",IF(H5>50,"B",IF(H5>40,"C",IF(H5>35,"D","Fail")))) -> B | N5: {=_xlfn.IFS(H5>60,"A",H5>50,"B",H5>40,"C",H5>=35,"D",H5<35,"Fail")} -> B | O5: {=IF(AND(B5:F5>35),"Pass","Fail")} -> Fail | P5: {=IF(OR(B5:F5>35),"Pass","Fail")} -> Pass | Q5: =RANK(H5,$H$2:$H$10,0) -> 4
A6: Name 1 | B6: 22 | C6: 79 | D6: 95 | E6: 16 | F6: 43 | G6: =SUM(B6:F6) -> 255 | H6: =AVERAGE(B6:F6) -> 51 | I6: =MAX(B6:F6) -> 95 | J6: =MIN(B6:F6) -> 16 | K6: =COUNT(B6:F6) -> 5 | L6: =IF(H6>35,"Pass","Fail") -> Pass | M6: =IF(H6>60,"A",IF(H6>50,"B",IF(H6>40,"C",IF(H6>35,"D","Fail")))) -> B | N6: {=_xlfn.IFS(H6>60,"A",H6>50,"B",H6>40,"C",H6>=35,"D",H6<35,"Fail")} -> B | O6: {=IF(AND(B6:F6>35),"Pass","Fail")} -> Fail | P6: {=IF(OR(B6:F6>35),"Pass","Fail")} -> Pass | Q6: =RANK(H6,$H$2:$H$10,0) -> 5 | V6: 5
A7: Name 1 | B7: 81 | C7: 12 | D7: 95 | E7: 17 | F7: 2 | G7: =SUM(B7:F7) -> 207 | H7: =AVERAGE(B7:F7) -> 41.4 | I7: =MAX(B7:F7) -> 95 | J7: =MIN(B7:F7) -> 2 | K7: =COUNT(B7:F7) -> 5 | L7: =IF(H7>35,"Pass","Fail") -> Pass | M7: =IF(H7>60,"A",IF(H7>50,"B",IF(H7>40,"C",IF(H7>35,"D","Fail")))) -> C | N7: {=_xlfn.IFS(H7>60,"A",H7>50,"B",H7>40,"C",H7>=35,"D",H7<35,"Fail")} -> C | O7: {=IF(AND(B7:F7>35),"Pass","Fail")} -> Fail | P7: {=IF(OR(B7:F7>35),"Pass","Fail")} -> Pass | Q7: =RANK(H7,$H$2:$H$10,0) -> 7
A8: Name 6 | B8: 16 | C8: 73 | D8: 7 | E8: 27 | F8: 81 | G8: =SUM(B8:F8) -> 204 | H8: =AVERAGE(B8:F8) -> 40.8 | I8: =MAX(B8:F8) -> 81 | J8: =MIN(B8:F8) -> 7 | K8: =COUNT(B8:F8) -> 5 | L8: =IF(H8>35,"Pass","Fail") -> Pass | M8: =IF(H8>60,"A",IF(H8>50,"B",IF(H8>40,"C",IF(H8>35,"D","Fail")))) -> C | N8: {=_xlfn.IFS(H8>60,"A",H8>50,"B",H8>40,"C",H8>=35,"D",H8<35,"Fail")} -> C | O8: {=IF(AND(B8:F8>35),"Pass","Fail")} -> Fail | P8: {=IF(OR(B8:F8>35),"Pass","Fail")} -> Pass | Q8: =RANK(H8,$H$2:$H$10,0) -> 8
A9: Name 3 | B9: 66 | C9: 42 | D9: 74 | E9: 41 | F9: 14 | G9: =SUM(B9:F9) -> 237 | H9: =AVERAGE(B9:F9) -> 47.4 | I9: =MAX(B9:F9) -> 74 | J9: =MIN(B9:F9) -> 14 | K9: =COUNT(B9:F9) -> 5 | L9: =IF(H9>35,"Pass","Fail") -> Pass | M9: =IF(H9>60,"A",IF(H9>50,"B",IF(H9>40,"C",IF(H9>35,"D","Fail")))) -> C | N9: {=_xlfn.IFS(H9>60,"A",H9>50,"B",H9>40,"C",H9>=35,"D",H9<35,"Fail")} -> C | O9: {=IF(AND(B9:F9>35),"Pass","Fail")} -> Fail | P9: {=IF(OR(B9:F9>35),"Pass","Fail")} -> Pass | Q9: =RANK(H9,$H$2:$H$10,0) -> 6
A10: Name 3 | B10: 20 | C10: 18 | D10: 32 | E10: 20 | F10: 7 | G10: =SUM(B10:F10) -> 97 | H10: =AVERAGE(B10:F10) -> 19.4 | I10: =MAX(B10:F10) -> 32 | J10: =MIN(B10:F10) -> 7 | K10: =COUNT(B10:F10) -> 5 | L10: =IF(H10>35,"Pass","Fail") -> Fail | M10: =IF(H10>60,"A",IF(H10>50,"B",IF(H10>40,"C",IF(H10>35,"D","Fail")))) -> Fail | N10: {=_xlfn.IFS(H10>60,"A",H10>50,"B",H10>40,"C",H10>=35,"D",H10<35,"Fail")} -> Fail | O10: {=IF(AND(B10:F10>35),"Pass","Fail")} -> Fail | P10: {=IF(OR(B10:F10>35),"Pass","Fail")} -> Fail | Q10: =RANK(H10,$H$2:$H$10,0) -> 9
A12: kth | B12: 2 | C12: 4 | D12: 1 | E12: 1 | F12: 1 | G12: 1 | H12: 1 | M12: Countif | O12: Sumif | Q12: Averageif
A13: Small | B13: =SMALL(B2:B10,B12) -> 20 | C13: =SMALL(C2:C10,C12) -> 42 | D13: =SMALL(D2:D10,D12) -> 7 | E13: =SMALL(E2:E10,E12) -> 16 | F13: =SMALL(F2:F10,F12) -> 2 | G13: =SMALL(G2:G10,G12) -> 97 | H13: =SMALL(H2:H10,H12) -> 19.4 | J13: Condition 1 | K13: Name 3 | M13: =COUNTIF(A2:A10,K13) -> 3 | O13: =SUMIF(A2:A10,K13,G2:G10) -> 627 | Q13: =AVERAGEIF(A2:A10,K13,G2:G10) -> 209
M14: =_xlfn.FORMULATEXT(M13) -> =COUNTIF(A2:A10,K13) | O14: =_xlfn.FORMULATEXT(O13) -> =SUMIF(A2:A10,K13,G2:G10) | Q14: =_xlfn.FORMULATEXT(Q13) -> =AVERAGEIF(A2:A10,K13,G2:G10)
A15: Large | B15: =LARGE(B2:B10,B12) -> 90 | C15: =LARGE(C2:C10,C12) -> 54 | D15: =LARGE(D2:D10,D12) -> 95 | E15: =LARGE(E2:E10,E12) -> 65 | F15: =LARGE(F2:F10,F12) -> 90 | G15: =LARGE(G2:G10,G12) -> 372 | H15: =LARGE(H2:H10,H12) -> 74.4
M16: Countifs | O16: Sumifs | Q16: Averageifs
B17: Randbetween | J17: Condition 2 | K17: >50 | M17: =COUNTIFS(A2:A10,K13,D2:D10,K17) -> 2 | O17: =SUMIFS(G2:G10,A2:A10,K13,B2:B10,K17) -> 530 | Q17: =AVERAGEIFS(G2:G10,A2:A10,K13,B2:B10,K17) -> 265
M18: =_xlfn.FORMULATEXT(M17) -> =COUNTIFS(A2:A10,K13,D2:D10,K17) | O18: =_xlfn.FORMULATEXT(O17) -> =SUMIFS(G2:G10,A2:A10,K13,B2:B10,K17) | Q18: =_xlfn.FORMULATEXT(Q17) -> =AVERAGEIFS(G2:G10,A2:A10,K13,B2:B10,K17)
A19: Employee | B19: Salary (K) | C19: Working Days | D19: bonus | G19: RandArray | M19: Not
A20: Emp 1 | B20: 31 | C20: 90 | D20: =IF(NOT(AND(B20>50)),B20,B20*50%) -> 31 | G20: 61 | H20: 55 | I20: 100 | M20: TRUE | N20: =NOT(M20) -> FALSE
A21: Emp 2 | B21: 42 | C21: 45 | D21: =IF(NOT(AND(B21>50)),B21,B21*50%) -> 42 | G21: 66 | H21: 92 | I21: 60 | M21: FALSE | N21: =NOT(M21) -> TRUE
A22: Emp 3 | B22: 40 | C22: 109 | D22: =IF(NOT(AND(B22>50)),B22,B22*50%) -> 40 | G22: 73 | H22: 97 | I22: 98
A23: Emp 4 | B23: 76 | C23: 115 | D23: =IF(NOT(AND(B23>50)),B23,B23*50%) -> 38 | G23: 67 | H23: 68 | I23: 98
A24: Emp 5 | B24: 64 | C24: 146 | D24: =IF(NOT(AND(B24>50)),B24,B24*50%) -> 32 | G24: 71 | H24: 95 | I24: 76
A25: Emp 6 | B25: 57 | C25: 117 | D25: =IF(NOT(AND(B25>50)),B25,B25*50%) -> 28.5 | G25: 60 | H25: 78 | I25: 63
A26: Emp 7 | B26: 88 | C26: 32 | D26: =IF(NOT(AND(B26>50)),B26,B26*50%) -> 44
C29: Iferror
A30: 100 | B30: A | C30: =IFERROR(A30/B30,"Check ") -> Check
B37: And | F37: Or | J37: Not | M37: XOR
B38: T | C38: T | D38: T | F38: T | G38: T | H38: T | J38: T | K38: F | M38: TRUE | N38: TRUE | O38: =_xlfn.XOR(M38:N38) -> FALSE
B39: T | C39: F | D39: F | F39: T | G39: F | H39: T | J39: F | K39: T | M39: TRUE | N39: FALSE | O39: =_xlfn.XOR(M39:N39) -> TRUE
B40: F | C40: T | D40: F | F40: F | G40: T | H40: T | M40: FALSE | N40: TRUE | O40: =_xlfn.XOR(M40:N40) -> TRUE
B41: F | C41: F | D41: F | F41: F | G41: F | H41: F | M41: FALSE | N41: FALSE | O41: =_xlfn.XOR(M41:N41) -> FALSE

Sheet Date & Time -24
A1: Control + : | B1: 45866
A2: Control + Shift +: | B2: 0.7625
A4: Today | B4: Now | C4: Day | D4: Month | E4: Year | F4: Date | G4: Hour | H4: Minute | I4: Second | J4: Time
A5: =TODAY() -> 46109 | B5: =NOW() -> 46109.619 | C5: =DAY(A5) -> 28 | D5: =MONTH(A5) -> 3 | E5: =YEAR(A5) -> 2026 | F5: =DATE(E5,D5,C5) -> 46109 | G5: =HOUR(B5) -> 14 | H5: =MINUTE(B5) -> 50 | I5: =SECOND(B5) -> 57 | J5: =TIME(G5,H5,I5) -> 0.61871528
A6: =_xlfn.FORMULATEXT(A5) -> =TODAY() | B6: =_xlfn.FORMULATEXT(B5) -> =NOW() | C6: =_xlfn.FORMULATEXT(C5) -> =DAY(A5) | D6: =_xlfn.FORMULATEXT(D5) -> =MONTH(A5) | E6: =_xlfn.FORMULATEXT(E5) -> =YEAR(A5) | F6: =_xlfn.FORMULATEXT(F5) -> =DATE(E5,D5,C5) | G6: =_xlfn.FORMULATEXT(G5) -> =HOUR(B5) | H6: =_xlfn.FORMULATEXT(H5) -> =MINUTE(B5) | ... J6: =_xlfn.FORMULATEXT(J5) -> =TIME(G5,H5,I5)
A8: Start Date | B8: End Date | E8: Start Date | F8: Number of Days | G8: Holiday
A9: 35248 | B9: =TODAY() -> 46109 | E9: 46031 | F9: 10 | G9: 46036
G10: 46038
A12: Days | B12: Days360 | C12: Datedif | E12: Workday | F12: Workday INTL | H12: Edate | I12: EoMonth
A13: =_xlfn.DAYS(B9,A9) -> 10861 | B13: =DAYS360(A9,B9) -> 10706 | C13: =DATEDIF(A9,B9,"Y") -> 29 | E13: =WORKDAY(E9,F9,G9:G10) -> 46049 | F13: =WORKDAY.INTL(E9,F9,11,G9:G10) -> 46045 | H13: =EDATE(E9,-3) -> 45939 | I13: =EOMONTH(E9,2) -> 46112
A14: =_xlfn.FORMULATEXT(A13) -> =DAYS(B9,A9) | B14: =_xlfn.FORMULATEXT(B13) -> =DAYS360(A9,B9) | C14: =_xlfn.FORMULATEXT(C13) -> =DATEDIF(A9,B9,"Y") | E14: =_xlfn.FORMULATEXT(E13) -> =WORKDAY(E9,F9,G9:G10) | F14: =_xlfn.FORMULATEXT(F13) -> =WORKDAY.INTL(E9,F9,11,G9:G10) | H14: =_xlfn.FORMULATEXT(H13) -> =EDATE(E9,-3) | I14: =_xlfn.FORMULATEXT(I13) -> =EOMONTH(E9,2)
A16: Start Date | B16: End Date | C16: Holiday | E16: Start Date | F16: End Date
A17: 46023 | B17: 46053 | C17: 46036 | E17: 35248 | F17: 45848
C18: 46038
A19: Networkdays | B19: NetworkdaysINTL | E19: Date Value | F19: Yearfarc | H19: Weeknum | I19: Weekday
A20: =NETWORKDAYS(A17,B17,C17:C18) -> 20 | B20: =NETWORKDAYS.INTL(A17,B17,11,C17:C18) -> 25 | E20: =DATEVALUE("11-1-26") -> 46033 | F20: =YEARFRAC(E17,F17,1) -> 29.019894 | H20: =WEEKNUM(TODAY(),2) -> 13 | I20: =WEEKDAY(TODAY(),2) -> 6
A21: =_xlfn.FORMULATEXT(A20) -> =NETWORKDAYS(A17,B17,C17:C18) | B21: =_xlfn.FORMULATEXT(B20) -> =NETWORKDAYS.INTL(A17,B17,11,C17:C18) | E21: =_xlfn.FORMULATEXT(E20) -> =DATEVALUE("11-1-26") | F21: =_xlfn.FORMULATEXT(F20) -> =YEARFRAC(E17,F17,1) | H21: =_xlfn.FORMULATEXT(H20) -> =WEEKNUM(TODAY(),2) | I21: =_xlfn.FORMULATEXT(I20) -> =WEEKDAY(TODAY(),2)
B23: 35248
A24: DD | B24: 02 | D24: MM | E24: 3 | H24: Text | I24: =TEXT(A9,"DD-DDD-MM-MMM-MMMM-YY-YYYY") -> 02-Tue-07-Jul-July-96-1996
A25: DDD | B25: Sun | D25: MMM | E25: Mar
A26: DDDD | B26: Sunday | D26: MMMM | E26: March
A28: YY | B28: 25
A29: YYYY | B29: 2025
B35: =DATEVALUE("31-12-1899") -> #VALUE!

Sheet Text Function
A1: Text | B1: Upper | C1: Lower | D1: Proper | E1: Len
A2: Develearn in computer class IN thane boy IN | B2: =UPPER(A2) -> DEVELEARN IN COMPUTER CLASS IN THANE BOY IN | C2: =LOWER(A2) -> develearn in computer class in thane boy in | D2: =PROPER(A2) -> Develearn In Computer Class In Thane Boy In | E2: =LEN(A2) -> 43
B3: =_xlfn.FORMULATEXT(B2) -> =UPPER(A2) | C3: =_xlfn.FORMULATEXT(C2) -> =LOWER(A2) | D3: =_xlfn.FORMULATEXT(D2) -> =PROPER(A2) | E3: =_xlfn.FORMULATEXT(E2) -> =LEN(A2)
B5: Find (Case Senstitive) | C5: Search | E5: Rept
A6: IN | B6: =FIND(A6,A2,FIND(A6,A2)+1) -> 42 | C6: =SEARCH(A6,A2,12) -> 29 | D6: Rohit | E6: =REPT(D6 & " ",5) -> Rohit Rohit Rohit Rohit Rohit
B7: =_xlfn.FORMULATEXT(B6) -> =FIND(A6,A2,FIND(A6,A2)+1) | C7: =_xlfn.FORMULATEXT(C6) -> =SEARCH(A6,A2,12) | E7: =_xlfn.FORMULATEXT(E6) -> =REPT(D6 & " ",5)
D8: 90 | E8: =REPT("|",D8) -> ||||||||||||||||||||||||||||||||||||||||||||||||||||||||||||||||||||||||||||||||||||||||||
A9: Rohit | B9: Exact (Case Senstitive) | C9: Direct (Not Case Senstitive) | E9: =_xlfn.FORMULATEXT(E8) -> =REPT("|",D8)
A10: rohit | B10: =EXACT(A9,A10) -> FALSE | C10: =A9=A10 -> TRUE
A12: Text | B12: Trim | C12: Subsititute (Case Senstitive) | D12: Replace
A13: Develearn class in thane class class | B13: =TRIM(A13) -> Develearn class in thane class class | C13: =TRIM(SUBSTITUTE(A13,"class","Group",3)) -> Develearn class in thane class Group | D13: =REPLACE(A13,FIND("class",A13),5,"Group") -> Develearn Group in thane class class
B14: =_xlfn.FORMULATEXT(B13) -> =TRIM(A13) | C14: =_xlfn.FORMULATEXT(C13) -> =TRIM(SUBSTITUTE(A13,"class","Group",3)) | D14: =_xlfn.FORMULATEXT(D13) -> =REPLACE(A13,FIND("class",A13),5,"Group")
A15: Rohit kumar jha | B15: =TRIM(A15) -> Rohit kumar jha | C15: =SUBSTITUTE(A15," ","") -> Rohitkumarjha | D15: =TRIM(REPLACE(B15,SEARCH("kumar",B15),5,"")) -> Rohit jha
B16: =_xludf.FORMULATEXT(B15) -> #NAME? | C16: =_xludf.FORMULATEXT(C15) -> #NAME? | D16: =_xludf.FORMULATEXT(D15) -> #NAME?
B19: Clean | D19: Char | E19: Code | F19: UNICODE | G19: UNICHAR
A20: Rohit kumar jha | B20: =CLEAN(A20) -> Rohit kumar jha | C20: 65 | D20: =CHAR(C20) -> A | E20: =CODE(D20) -> 65 | F20: =_xlfn.UNICODE(G20) -> 128077 | G20: =_xlfn.UNICHAR(128077) -> 👍
B21: =_xludf.FORMULATEXT(B20) -> #NAME? | D21: =_xludf.FORMULATEXT(D20) -> #NAME? | E21: =_xludf.FORMULATEXT(E20) -> #NAME? | F21: =_xludf.FORMULATEXT(G20) -> #NAME? | G21: =_xludf.FORMULATEXT(#REF!) -> #NAME?
A23: Text 1 | B23: Text 2 | C23: Text 2 | D23: Concat | E23: Text Join | F23: &
A24: Rohit | B24: kumar | C24: Jha | D24: =_xlfn.CONCAT(A24," ",B24,C24) -> Rohit kumarJha | E24: =_xlfn.TEXTJOIN("-",TRUE,A24,B24,C24) -> Rohit-kumar-Jha
D25: =_xlfn.FORMULATEXT(D24) -> =CONCAT(A24," ",B24,C24) | E25: =_xlfn.TEXTJOIN(" ",TRUE,A24:C24) -> Rohit kumar Jha | F25: =_xlfn.FORMULATEXT(F24) -> #N/A
A27: Number | B27: Left | C27: Right | D27: Mid
A28: 9876543210 | B28: =LEFT(A28,5) -> 98765 | C28: =RIGHT(A28,5) -> 43210 | D28: =MID(A28,5,4) -> 5432
B29: =_xlfn.FORMULATEXT(B28) -> =LEFT(A28,5) | C29: =_xlfn.FORMULATEXT(C28) -> =RIGHT(A28,5) | D29: =_xlfn.FORMULATEXT(D28) -> =MID(A28,5,4)
A30: Name
A31: Rohit kumaar Jha | B31: =LEFT(A31,FIND(" ",A31)-1) -> Rohit | C31: =RIGHT(A31,LEN(A31)-FIND(" ",A31,FIND(" ",A31)+1)) -> Jha | E31: =MID(A31, FIND(" ", A31)+1, FIND(" ", A31, FIND(" ", A31)+1) - FIND(" ", A31)-1) -> kumaar
A33: Five Star
A34: 5 | B34: =REPT(_xlfn.UNICHAR(128077),A34) & REPT(_xlfn.UNICHAR(128078),5-A34) -> 👍👍👍👍👍
A35: 4 | B35: =REPT(_xlfn.UNICHAR(128077),A35) & REPT(_xlfn.UNICHAR(128078),5-A35) -> 👍👍👍👍👎
A36: 2 | B36: =REPT(_xlfn.UNICHAR(128077),A36) & REPT(_xlfn.UNICHAR(128078),5-A36) -> 👍👍👎👎👎
A37: 3 | B37: =REPT(_xlfn.UNICHAR(128077),A37) & REPT(_xlfn.UNICHAR(128078),5-A37) -> 👍👍👍👎👎
A38: 1 | B38: =REPT(_xlfn.UNICHAR(128077),A38) & REPT(_xlfn.UNICHAR(128078),5-A38) -> 👍👎👎👎👎
A41: Rohit,Amit@Ganesh,Rahul | B41: {=_xlfn.TEXTSPLIT(A41,,",")} -> Rohit | C41: =_xlfn.TEXTBEFORE(A41,"@") -> Rohit,Amit | D41: {=_xlfn.TEXTSPLIT(_xlfn.TEXTAFTER(A41,"@"),,",")} -> Ganesh
B42: Amit@Ganesh | D42: Rahul
B43: Rahul

Sheet Database Function If Functions
A1: ID | B1: Date | C1: Region | D1: Salesperson | E1: Product | F1: Units Sold | G1: Unit Price | H1: Total Sales | K1: ID | L1: Date | M1: Region | N1: Salesperson | O1: Product | P1: Units Sold | Q1: Unit Price | R1: Total Sales
A2: 1 | B2: 45662 | C2: East | D2: Alice | E2: Printer | F2: 5 | G2: 150 | H2: =F2*G2 -> 750 | M2: North
A3: 2 | B3: 45665 | C3: West | D3: Bob | E3: Monitor | F3: 3 | G3: 200 | H3: =F3*G3 -> 600
A4: 3 | B4: 45667 | C4: East | D4: Charlie | E4: Laptop | F4: 3 | G4: 1200 | H4: =F4*G4 -> 3600
A5: 4 | B5: 45667 | C5: South | D5: Alice | E5: Printer | F5: 6 | G5: 150 | H5: =F5*G5 -> 900
A6: 5 | B6: 45672 | C6: North | D6: David | E6: Monitor | F6: 6 | G6: 200 | H6: =F6*G6 -> 1200
A7: 6 | B7: 45674 | C7: East | D7: Bob | E7: Laptop | F7: 1 | G7: 1200 | H7: =F7*G7 -> 1200
A8: 7 | B8: 45677 | C8: West | D8: Charlie | E8: Printer | F8: 3 | G8: 150 | H8: =F8*G8 -> 450
A9: 8 | B9: 45682 | C9: North | D9: Alice | E9: Monitor | F9: 4 | G9: 200 | H9: =F9*G9 -> 800
A10: 9 | B10: 45685 | C10: South | D10: David | E10: Laptop | F10: 5 | G10: 1200 | H10: =F10*G10 -> 6000
A11: 10 | B11: 45687 | C11: East | D11: Bob | E11: Printer | F11: 2 | G11: 150 | H11: =F11*G11 -> 300
B13: Total Sales | C13: Unit Price | F13: Total Sales | J13: Total Sales | M13: Total Sales
A14: Dget | B14: =DGET(A1:H11,B13,K1:R2) -> #NUM! | E14: Dcount | F14: =DCOUNT(A1:H11,F13,K1:R2) -> 2 | I14: Dmax | J14: =DMAX(A1:H11,J13,K1:R2) -> 1200 | L14: Daverage
B15: =_xlfn.FORMULATEXT(B14) -> =DGET(A1:H11,B13,K1:R2) | C15: =_xlfn.FORMULATEXT(C14) -> #N/A | F15: =_xlfn.FORMULATEXT(F14) -> =DCOUNT(A1:H11,F13,K1:R2) | J15: =_xlfn.FORMULATEXT(J14) -> =DMAX(A1:H11,J13,K1:R2) | M15: =_xlfn.FORMULATEXT(M14) -> #N/A
B17: Total Sales | F17: Region | J17: Total Sales
A18: Dsum | B18: =DSUM(A1:H11,B17,K1:R2) -> 2000 | E18: DcountA | F18: =DCOUNTA(A1:H11,F17,K1:R2) -> 2 | I18: Dmin | J18: =DMIN(A1:H11,J17,K1:R2) -> 800
B19: =_xlfn.FORMULATEXT(B18) -> =DSUM(A1:H11,B17,K1:R2) | F19: =_xlfn.FORMULATEXT(F18) -> =DCOUNTA(A1:H11,F17,K1:R2) | J19: =_xlfn.FORMULATEXT(J18) -> =DMIN(A1:H11,J17,K1:R2)

Sheet Filter and Sort
A1: Product ID | B1: Product Name | C1: Category | D1: Region | E1: Salesperson | F1: Units Sold | G1: Unit Price | H1: Sale Value | I1: Month
A2: P001 | B2: Laptop | C2: Electronics | D2: North | E2: Alice | F2: 10 | G2: 600 | H2: =PRODUCT(F2,G2) -> 6000 | I2: January
A3: P002 | B3: Mobile | C3: Electronics | D3: South | E3: Bob | F3: 15 | G3: 400 | H3: =PRODUCT(F3,G3) -> 6000 | I3: January | M3: First Use | N3: =SUM(OFFSET(A1,1,7,9,1)) -> 34900
A4: P003 | B4: Chair | C4: Furniture | D4: East | E4: Charlie | F4: 20 | G4: 100 | H4: =PRODUCT(F4,G4) -> 2000 | I4: February
A5: P004 | B5: Table | C5: Furniture | D5: West | E5: Alice | F5: 12 | G5: 200 | H5: =PRODUCT(F5,G5) -> 2400 | I5: February
A6: P005 | B6: Laptop | C6: Electronics | D6: North | E6: Bob | F6: 8 | G6: 600 | H6: =PRODUCT(F6,G6) -> 4800 | I6: March | N6: =SUM(OFFSET(A1,COUNTA(H1:H10)-1,7,-3,1)) -> 11200
A7: P006 | B7: Sofa | C7: Furniture | D7: South | E7: Charlie | F7: 5 | G7: 500 | H7: =PRODUCT(F7,G7) -> 2500 | I7: March
A8: P007 | B8: Mobile | C8: Electronics | D8: East | E8: Alice | F8: 18 | G8: 400 | H8: =PRODUCT(F8,G8) -> 7200 | I8: April
A9: P008 | B9: Table | C9: Furniture | D9: West | E9: Rohit | F9: 10 | G9: 200 | H9: =PRODUCT(F9,G9) -> 2000 | I9: April
A10: P008 | B10: Table | C10: Furniture | D10: West | E10: Rohit | F10: 10 | G10: 200 | H10: =PRODUCT(F10,G10) -> 2000 | I10: April
B11: =_xlfn.FORMULATEXT(B13) -> =FILTER(A1:I9,E1:E9=B12,"Na")
A12: Filter | B12: Bob
B13: {=_xlfn._xlws.FILTER(A1:I9,E1:E9=B12,"Na")} -> P002 | C13: Mobile | D13: Electronics | E13: South | F13: Bob | G13: 15 | H13: 400 | I13: 6000 | J13: January
B14: P005 | C14: Laptop | D14: Electronics | E14: North | F14: Bob | G14: 8 | H14: 600 | I14: 4800 | J14: March
A22: Sort | B22: =_xlfn.FORMULATEXT(B23) -> =SORT(A2:I9,4,-1,FALSE)
B23: {=_xlfn._xlws.SORT(A2:I9,4,-1,FALSE)} -> P004 | C23: Table | D23: Furniture | E23: West | F23: Alice | G23: 12 | H23: 200 | I23: 2400 | J23: February
B24: P008 | C24: Table | D24: Furniture | E24: West | F24: Rohit | G24: 10 | H24: 200 | I24: 2000 | J24: April
B25: P002 | C25: Mobile | D25: Electronics | E25: South | F25: Bob | G25: 15 | H25: 400 | I25: 6000 | J25: January
B26: P006 | C26: Sofa | D26: Furniture | E26: South | F26: Charlie | G26: 5 | H26: 500 | I26: 2500 | J26: March
B27: P001 | C27: Laptop | D27: Electronics | E27: North | F27: Alice | G27: 10 | H27: 600 | I27: 6000 | J27: January
B28: P005 | C28: Laptop | D28: Electronics | E28: North | F28: Bob | G28: 8 | H28: 600 | I28: 4800 | J28: March
B29: P003 | C29: Chair | D29: Furniture | E29: East | F29: Charlie | G29: 20 | H29: 100 | I29: 2000 | J29: February
B30: P007 | C30: Mobile | D30: Electronics | E30: East | F30: Alice | G30: 18 | H30: 400 | I30: 7200 | J30: April
A32: Unique | B32: =_xlfn.FORMULATEXT(B33) -> =UNIQUE(I2:I10,FALSE,TRUE)
B33: {=_xlfn.UNIQUE(I2:I10,FALSE,TRUE)} -> #VALUE!

Sheet Lookup Function
A1: Vertical Data | K1: Horizontal Data | M1: Transpose | N1: =_xlfn.FORMULATEXT(K2) -> =TRANSPOSE(A2:I10)
A2: Product ID | B2: Product Name | C2: Category | D2: Region | E2: Salesperson | F2: Units Sold | G2: Unit Price | H2: Sale Value | I2: Month | K2: {=TRANSPOSE(A2:I10)} -> Product ID | L2: P001 | M2: P002 | N2: P003 | O2: P004 | P2: P005 | Q2: P006 | R2: P007 | S2: P008
A3: P001 | B3: Laptop | C3: Electronics | D3: North | E3: Alice | F3: 0.9 | G3: 600 | H3: =PRODUCT(F3,G3) -> 540 | I3: January | K3: Product Name | L3: Laptop | M3: Mobile | N3: Chair | O3: Table | P3: Laptop | Q3: Sofa | R3: Mobile | S3: Table
A4: P002 | B4: Mobile | C4: Electronics | D4: South | E4: Bob | F4: 0.7 | G4: 400 | H4: =PRODUCT(F4,G4) -> 280 | I4: January | K4: Category | L4: Electronics | M4: Electronics | N4: Furniture | O4: Furniture | P4: Electronics | Q4: Furniture | R4: Electronics | S4: Furniture
A5: P003 | B5: Chair | C5: Furniture | D5: East | E5: Charlie | F5: 0.5 | G5: 100 | H5: =PRODUCT(F5,G5) -> 50 | I5: February | K5: Region | L5: North | M5: South | N5: East | O5: West | P5: North | Q5: South | R5: East | S5: West
A6: P004 | B6: Table | C6: Furniture | D6: West | E6: Alice | F6: 0.6 | G6: 200 | H6: =PRODUCT(F6,G6) -> 120 | I6: February | K6: Salesperson | L6: Alice | M6: Bob | N6: Charlie | O6: Alice | P6: Bob | Q6: Charlie | R6: Alice | S6: Bob
A7: P005 | B7: Laptop | C7: Electronics | D7: North | E7: Bob | F7: 0.8 | G7: 600 | H7: =PRODUCT(F7,G7) -> 480 | I7: March | K7: Units Sold | L7: 0.9 | M7: 0.7 | N7: 0.5 | O7: 0.6 | P7: 0.8 | Q7: 0.5 | R7: 0.4 | S7: 0.9
A8: P006 | B8: Sofa | C8: Furniture | D8: South | E8: Charlie | F8: 0.5 | G8: 500 | H8: =PRODUCT(F8,G8) -> 250 | I8: March | K8: Unit Price | L8: 600 | M8: 400 | N8: 100 | O8: 200 | P8: 600 | Q8: 500 | R8: 400 | S8: 200
A9: P007 | B9: Mobile | C9: Electronics | D9: East | E9: Alice | F9: 0.4 | G9: 400 | H9: =PRODUCT(F9,G9) -> 160 | I9: April | K9: Sale Value | L9: 540 | M9: 280 | N9: 50 | O9: 120 | P9: 480 | Q9: 250 | R9: 160 | S9: 180
A10: P008 | B10: Table | C10: Furniture | D10: West | E10: Bob | F10: 0.9 | G10: 200 | H10: =PRODUCT(F10,G10) -> 180 | I10: May | K10: Month | L10: January | M10: January | N10: February | O10: February | P10: March | Q10: March | R10: April | S10: May
A13: VLOOKUP | K13: HLOOKUP
A15: Lookup Value | B15: Result | K15: Lookup Value | L15: Result
A16: P004 | B16: =VLOOKUP(A16,A2:I10,6,0) -> 0.6 | K16: P007 | L16: =HLOOKUP(K16,_xlfn.ANCHORARRAY(K2),6,0) -> 0.4
A18: Xlookup | K18: Xlookup
A19: Lookup Value | B19: Result | K19: Lookup Value | L19: Result
A20: P008 | B20: =_xlfn.XLOOKUP(A20,A2:A10,I2:I10,"NA",0,1) -> May | K20: P003 | L20: =_xlfn.XLOOKUP(K20,K2:S2,K9:S9,"NA",0,1) -> 50
A24: Product ID | B24: Product Name | C24: Category | D24: Region | E24: Salesperson | F24: Units Sold | G24: Unit Price | H24: Sale Value | I24: Month | J24: Supplier | N24: Supplier | O24: Supplier | P24: City
A25: P001 | B25: Laptop | C25: Electronics | D25: North | E25: Alice | F25: 10 | G25: 600 | H25: =PRODUCT(F25,G25) -> 6000 | I25: January | J25: Supplier 1 | N25: Supplier 1 | O25: Supplier Name 1 | P25: Mumbai
A26: P002 | B26: Mobile | C26: Electronics | D26: South | E26: Bob | F26: 15 | G26: 400 | H26: =PRODUCT(F26,G26) -> 6000 | I26: January | J26: Supplier 2 | N26: Supplier 2 | O26: Supplier Name 2 | P26: Delhi
A27: P003 | B27: Chair | C27: Furniture | D27: East | E27: Charlie | F27: 20 | G27: 100 | H27: =PRODUCT(F27,G27) -> 2000 | I27: February | J27: Supplier 3 | N27: Supplier 3 | O27: Supplier Name 3 | P27: Patna
A28: P004 | B28: Table | C28: Furniture | D28: West | E28: Alice | F28: 12 | G28: 200 | H28: =PRODUCT(F28,G28) -> 2400 | I28: February | J28: Supplier 1
A29: P005 | B29: Laptop | C29: Electronics | D29: North | E29: Bob | F29: 8 | G29: 600 | H29: =PRODUCT(F29,G29) -> 4800 | I29: March | J29: Supplier 2
A30: P006 | B30: Sofa | C30: Furniture | D30: South | E30: Charlie | F30: 5 | G30: 500 | H30: =PRODUCT(F30,G30) -> 2500 | I30: March | J30: Supplier 3
A31: P007 | B31: Mobile | C31: Electronics | D31: East | E31: Alice | F31: 18 | G31: 400 | H31: =PRODUCT(F31,G31) -> 7200 | I31: April | J31: Supplier 1
A32: P008 | B32: Table | C32: Furniture | D32: West | E32: Bob | F32: 10 | G32: 200 | H32: =PRODUCT(F32,G32) -> 2000 | I32: May | J32: Supplier 2
N33: Nested V Lookup
A34: Vlookup with Match | N34: Lookup Value | O34: City
A35: Lookup Value | B35: Salesperson | N35: P007 | O35: =VLOOKUP(VLOOKUP(N35,A24:J32,10,0),N24:P27,3,0) -> Mumbai
A36: P006 | B36: =VLOOKUP(A36,A24:J32,MATCH(B35,A24:J24,0),0) -> Charlie
A38: Vlookup With Array
A39: Product ID | B39: Product Name | C39: Category | D39: Region | E39: Units Sold | F39: Salesperson | G39: Unit Price | H39: Sale Value | I39: Month | J39: Supplier
A40: P007 | B40: {=VLOOKUP(A40,A24:J32,{2,3,4,5,6,7,8,9,10},0)} -> Mobile | C40: Electronics | D40: East | E40: Alice | F40: 18 | G40: 400 | H40: 7200 | I40: April | J40: Supplier 1
A46: Salary | B46: Tax | E46: Salary | F46: Tax
A47: 0 | B47: 0 | E47: 5000 | F47: =VLOOKUP(E47,A46:B52,2,1) -> 0
A48: 100000 | B48: 0.02
A49: 500000 | B49: 0.05
A50: 800000 | B50: 0.1
A51: 1200000 | B51: 0.15
A52: 1500000 | B52: 0.3

Sheet FINANCIAL
A1: Loan | B1: PV | C1: 24990 | F1: MONTH | G1: IPMT | H1: PPMT | I1: TOTAL
A2: Rate (Annual) | C2: 0.17 | F2: 1 | G2: =IFERROR(-IPMT($C$2/12,F2,$C$3,$C$1),0) -> 354.025 | H2: =IFERROR(-PPMT($C$2/12,F2,$C$3,$C$1),0) -> 2623.0102 | I2: =SUM(G2:H2) -> 2977.0352 | S2: IPMT
A3: Month | B3: Nper | C3: 9 | F3: 2 | G3: =IFERROR(-IPMT($C$2/12,F3,$C$3,$C$1),0) -> 316.86569 | H3: =IFERROR(-PPMT($C$2/12,F3,$C$3,$C$1),0) -> 2660.1695 | I3: =SUM(G3:H3) -> 2977.0352 | L3: Day 1 | O3: 20 | P3: =O3*0.02% -> 0.004 | S3: PPMT
F4: 3 | G4: =IFERROR(-IPMT($C$2/12,F4,$C$3,$C$1),0) -> 279.17995 | H4: =IFERROR(-PPMT($C$2/12,F4,$C$3,$C$1),0) -> 2697.8553 | I4: =SUM(G4:H4) -> 2977.0352 | S4: PMT
A5: PMT/EMI | C5: =-PMT(C2/12,C3,C1) -> 2977.0352 | F5: 4 | G5: =IFERROR(-IPMT($C$2/12,F5,$C$3,$C$1),0) -> 240.96034 | H5: =IFERROR(-PPMT($C$2/12,F5,$C$3,$C$1),0) -> 2736.0749 | I5: =SUM(G5:H5) -> 2977.0352 | S5: RATE
A6: Total Pay | C6: =C5*C3 -> 26793.317 | F6: 5 | G6: =IFERROR(-IPMT($C$2/12,F6,$C$3,$C$1),0) -> 202.19928 | H6: =IFERROR(-PPMT($C$2/12,F6,$C$3,$C$1),0) -> 2774.836 | I6: =SUM(G6:H6) -> 2977.0352 | M6: switch | S6: NPER
A7: Interest | C7: =C6-C1 -> 1803.3171 | F7: 6 | G7: =IFERROR(-IPMT($C$2/12,F7,$C$3,$C$1),0) -> 162.8891 | H7: =IFERROR(-PPMT($C$2/12,F7,$C$3,$C$1),0) -> 2814.1461 | I7: =SUM(G7:H7) -> 2977.0352 | M7: choose | S7: PV
F8: 7 | G8: =IFERROR(-IPMT($C$2/12,F8,$C$3,$C$1),0) -> 123.02203 | H8: =IFERROR(-PPMT($C$2/12,F8,$C$3,$C$1),0) -> 2854.0132 | I8: =SUM(G8:H8) -> 2977.0352 | M8: cell | S8: FV
A9: PV | C9: =PV(C2/12,C3,-C5) -> 24990 | F9: 8 | G9: =IFERROR(-IPMT($C$2/12,F9,$C$3,$C$1),0) -> 82.590176 | H9: =IFERROR(-PPMT($C$2/12,F9,$C$3,$C$1),0) -> 2894.4451 | I9: =SUM(G9:H9) -> 2977.0352 | M9: indirect | S9: Switch
F10: 9 | G10: =IFERROR(-IPMT($C$2/12,F10,$C$3,$C$1),0) -> 41.585537 | H10: =IFERROR(-PPMT($C$2/12,F10,$C$3,$C$1),0) -> 2935.4497 | I10: =SUM(G10:H10) -> 2977.0352
A11: pv | C11: 1000 | F11: 10 | G11: =IFERROR(-IPMT($C$2/12,F11,$C$3,$C$1),0) -> 0 | H11: =IFERROR(-PPMT($C$2/12,F11,$C$3,$C$1),0) -> 0 | I11: =SUM(G11:H11) -> 0
A12: EMI | C12: 100 | F12: 11 | G12: =IFERROR(-IPMT($C$2/12,F12,$C$3,$C$1),0) -> 0 | H12: =IFERROR(-PPMT($C$2/12,F12,$C$3,$C$1),0) -> 0 | I12: =SUM(G12:H12) -> 0
A13: Rate | C13: 0.1 | F13: 12 | G13: =IFERROR(-IPMT($C$2/12,F13,$C$3,$C$1),0) -> 0 | H13: =IFERROR(-PPMT($C$2/12,F13,$C$3,$C$1),0) -> 0 | I13: =SUM(G13:H13) -> 0
A14: Nper | C14: 10 | F14: 13 | G14: =IFERROR(-IPMT($C$2/12,F14,$C$3,$C$1),0) -> 0 | H14: =IFERROR(-PPMT($C$2/12,F14,$C$3,$C$1),0) -> 0 | I14: =SUM(G14:H14) -> 0 | M14: Name 1 | N14: 10
A15: FV | C15: =-FV(C13/12,C14,C12,C11) -> 2124.8744 | F15: 14 | G15: =IFERROR(-IPMT($C$2/12,F15,$C$3,$C$1),0) -> 0 | H15: =IFERROR(-PPMT($C$2/12,F15,$C$3,$C$1),0) -> 0 | I15: =SUM(G15:H15) -> 0 | M15: Name 2 | N15: 60
F16: 15 | G16: =IFERROR(-IPMT($C$2/12,F16,$C$3,$C$1),0) -> 0 | H16: =IFERROR(-PPMT($C$2/12,F16,$C$3,$C$1),0) -> 0 | I16: =SUM(G16:H16) -> 0 | M16: Name 3 | N16: 50
A17: Nper | C17: =NPER(C13/12,C12,C11,-C15) -> 10 | F17: 16 | G17: =IFERROR(-IPMT($C$2/12,F17,$C$3,$C$1),0) -> 0 | H17: =IFERROR(-PPMT($C$2/12,F17,$C$3,$C$1),0) -> 0 | I17: =SUM(G17:H17) -> 0 | M17: Name 4 | N17: 40
F18: Total | G18: =SUM(G2:G17) -> 1803.3171 | H18: =SUM(H2:H17) -> 24990 | I18: =SUM(I2:I17) -> 26793.317 | M18: Name 5 | N18: 30
A19: Rate | C19: =RATE(C14,C12,C11,-C15,0)*12 -> 0.1
M20: Name 3 | N20: {=_xludf.SWITCH(M20,M14,N14,M15,N15,M16,N16,M17,N17,M18,N18)} -> #NAME?

Sheet Index Match
A4: Product ID | B4: Product Name | C4: Category | D4: Region | E4: Salesperson | F4: Units Sold | G4: Unit Price | H4: Sale Value | I4: Month
A5: P001 | B5: Laptop | C5: Electronics | D5: North | E5: Alice | F5: 10 | G5: 600 | H5: =PRODUCT(F5,G5) -> 6000 | I5: January
A6: P002 | B6: Mobile | C6: Electronics | D6: South | E6: Bob | F6: 15 | G6: 400 | H6: =PRODUCT(F6,G6) -> 6000 | I6: January
A7: P003 | B7: Chair | C7: Furniture | D7: East | E7: Charlie | F7: 20 | G7: 100 | H7: =PRODUCT(F7,G7) -> 2000 | I7: February
A8: P004 | B8: Table | C8: Furniture | D8: West | E8: Alice | F8: 12 | G8: 200 | H8: =PRODUCT(F8,G8) -> 2400 | I8: February
A9: P005 | B9: Laptop | C9: Electronics | D9: North | E9: Bob | F9: 8 | G9: 600 | H9: =PRODUCT(F9,G9) -> 4800 | I9: March
A10: P006 | B10: Sofa | C10: Furniture | D10: South | E10: Charlie | F10: 5 | G10: 500 | H10: =PRODUCT(F10,G10) -> 2500 | I10: March
A11: P007 | B11: Mobile | C11: Electronics | D11: East | E11: Alice | F11: 18 | G11: 400 | H11: =PRODUCT(F11,G11) -> 7200 | I11: April
A12: P008 | B12: Table | C12: Furniture | D12: West | E12: Bob | F12: 10 | G12: 200 | H12: =PRODUCT(F12,G12) -> 2000 | I12: May
A14: Index & Match | K14: Match | L14: Value Ka position
J15: P008 | K15: =MATCH(J15,A4:A12,0) -> 9
A16: Product ID | B16: P005 | K16: =_xludf.FORMULATEXT(K15) -> #NAME?
A17: Detail | B17: Product Name | K17: Match
J18: Region | K18: =MATCH(J18,A4:I4,0) -> 4
A19: Result | B19: =INDEX(A4:I12,MATCH(B16,A4:A12,0),MATCH(B17,A4:I4,0)) -> Laptop
B20: =_xlfn.FORMULATEXT(B19) -> =INDEX(A4:I12,MATCH(B16,A4:A12,0),MATCH(B17,A4:I4,0)) | K20: Index | L20: Position Ka Value
L21: =INDEX(A4:I12,6,4) -> North

Sheet Hw Sheet
A1: Product ID | B1: Product Name | C1: Category | D1: Region | E1: Salesperson | F1: Units Sold | G1: Unit Price | H1: Sale Value | I1: Month
A2: P001 | B2: Laptop | C2: Electronics | D2: North | E2: Alice | F2: 10 | G2: 600 | I2: January
A3: P002 | B3: Mobile | C3: Electronics | D3: South | E3: Bob | F3: 15 | G3: 400 | I3: January
A4: P003 | B4: Chair | C4: Furniture | D4: East | E4: Charlie | F4: 20 | G4: 100 | I4: February
A5: P004 | B5: Table | C5: Furniture | D5: West | E5: Alice | F5: 12 | G5: 200 | I5: February
A6: P005 | B6: Laptop | C6: Electronics | D6: North | E6: Bob | F6: 8 | G6: 600 | I6: March
A7: P006 | B7: Sofa | C7: Furniture | D7: South | E7: Charlie | F7: 5 | G7: 500 | I7: March
A8: P007 | B8: Mobile | C8: Electronics | D8: East | E8: Alice | F8: 18 | G8: 400 | I8: April
A9: P008 | B9: Table | C9: Furniture | D9: West | E9: Bob | F9: 10 | G9: 200 | I9: April
A11: Problem
A12: 1 | B12: Find total Sales
A13: 2 | B13: Calculate total Sale Value for Furniture in West.
A14: 3 | B14: Find average Units Sold for same criteria.
A15: 4 | B15: Get maximum Unit Price of matching records.
A16: 5 | B16: Get minimum Units Sold.
A17: 5 | B17: Count how many sales match the criteria.
A18: 5 | B18: calculate total Sale Value for Alice in April.
A19: 5 | B19: count how many items Alice sold in April.

Sheet Sheet5
A1: Product ID | B1: Product Name | C1: Category | D1: Region | E1: Salesperson | F1: Units Sold | G1: Unit Price | H1: Sale Value | I1: Month
A2: P001 | B2: Laptop | C2: Electronics | D2: North | E2: Alice | F2: =VLOOKUP(A2,'Lookup Function'!$A$2:$I$10,6,0) -> 0.9 | G2: 600 | H2: =PRODUCT(F2,G2) -> 540 | I2: January | L2: 10
A3: P004 | B3: Table | C3: Furniture | D3: West | E3: Alice | F3: =VLOOKUP(A3,'Lookup Function'!$A$2:$I$10,6,0) -> 0.6 | G3: 200 | H3: =PRODUCT(F3,G3) -> 120 | I3: February | L3: 12
A4: P007 | B4: Mobile | C4: Electronics | D4: East | E4: Alice | F4: =VLOOKUP(A4,'Lookup Function'!$A$2:$I$10,6,0) -> 0.4 | G4: 400 | H4: =PRODUCT(F4,G4) -> 160 | I4: April | L4: 18
A5: P002 | B5: Mobile | C5: Electronics | D5: South | E5: Bob | F5: =VLOOKUP(A5,'Lookup Function'!$A$2:$I$10,6,0) -> 0.7 | G5: 400 | H5: =PRODUCT(F5,G5) -> 280 | I5: January | L5: 15 | O5: =SUM(F2,F5,F9) -> 2.1
A6: P005 | B6: Laptop | C6: Electronics | D6: North | E6: Bob | F6: =VLOOKUP(A6,'Lookup Function'!$A$2:$I$10,6,0) -> 0.8 | G6: 600 | H6: =PRODUCT(F6,G6) -> 480 | I6: March | L6: 8
A7: P008 | B7: Table | C7: Furniture | D7: West | E7: Bob | F7: =VLOOKUP(A7,'Lookup Function'!$A$2:$I$10,6,0) -> 0.9 | G7: 200 | H7: =PRODUCT(F7,G7) -> 180 | I7: May | L7: 10
A8: P003 | B8: Chair | C8: Furniture | D8: East | E8: Charlie | F8: =VLOOKUP(A8,'Lookup Function'!$A$2:$I$10,6,0) -> 0.5 | G8: 100 | H8: =PRODUCT(F8,G8) -> 50 | I8: February | L8: 20
A9: P006 | B9: Sofa | C9: Furniture | D9: South | E9: Charlie | F9: =VLOOKUP(A9,'Lookup Function'!$A$2:$I$10,6,0) -> 0.5 | G9: 500 | H9: =PRODUCT(F9,G9) -> 250 | I9: March | L9: 5

Sheet Sheet1

Sheet Homework
A1: Home
A2: 1 | B2: Formate Painter
A3: 2 | B3: Wrap text
A4: 3 | B4: Shink to Fit
A5: 4 | B5: Center Across Selection
A6: 5 | B6: Number formatting
A7: 6 | B7: Make a Marksheet with Conditional Formatting With Formula
A21: 7 | B21: Filter
A22: 8 | B22: Custom sort

Sheet Sheet3
A1: Sr. No | B1: Name | C1: Sub 1 | D1: Sub 2 | E1: Sub 3 | F1: Sub 4 | G1: Sub 5 | H1: Sub 6 | I1: Sub 7 | J1: Total
A2: 1 | B2: Student 3 | C2: 71 | D2: 11 | E2: 33 | F2: 10 | G2: 38 | H2: 48 | I2: 33 | J2: =SUM(C2:I2) -> 244
A3: 2 | B3: Student 1 | C3: 60 | D3: 83 | E3: 21 | F3: 16 | G3: 34 | H3: 3 | I3: 99 | J3: =SUM(C3:I3) -> 316
A4: 5 | B4: Student 8 | C4: 36 | D4: 11 | E4: 68 | F4: 54 | G4: 22 | H4: 84 | I4: 82 | J4: =SUM(C4:I4) -> 357
A5: 6 | B5: Student 1 | C5: 95 | D5: 1 | E5: 9 | F5: 70 | G5: 22 | H5: 13 | I5: 47 | J5: =SUM(C5:I5) -> 257
A6: 7 | B6: Student 4 | C6: 29 | D6: 50 | E6: 62 | F6: 83 | G6: 63 | H6: 67 | I6: 2 | J6: =SUM(C6:I6) -> 356
A7: 3 | B7: Student 2 | C7: 44 | D7: 46 | E7: 86 | F7: 35 | G7: 97 | H7: 20 | I7: 37 | J7: =SUM(C7:I7) -> 365
A8: 4 | B8: Student 9 | C8: 63 | D8: 16 | E8: 64 | F8: 49 | G8: 14 | H8: 72 | I8: 60 | J8: =SUM(C8:I8) -> 338
A9: 8 | B9: Student 1 | C9: 42 | D9: 79 | E9: 81 | F9: 85 | G9: 7 | H9: 72 | I9: 94 | J9: =SUM(C9:I9) -> 460
A10: 9 | B10: Student 6 | C10: 70 | D10: 35 | E10: 77 | F10: 96 | G10: 80 | H10: 30 | I10: 86 | J10: =SUM(C10:I10) -> 474
A13: Sr. No | B13: Name | C13: Sub 1 | D13: Sub 2 | E13: Sub 3 | F13: Sub 4 | G13: Sub 5 | H13: Sub 6 | I13: Sub 7 | J13: Total
B14: Student 1 | E14: >20

Sheet Sheet2
A1: Sr. No | B1: Name | C1: Sub 1 | D1: Sub 2 | E1: Sub 3 | F1: Sub 4 | G1: Sub 5 | H1: Sub 6 | I1: Sub 7 | J1: Total
A2: 2 | B2: Student 1 | C2: 60 | D2: 83 | E2: 21 | F2: 16 | G2: 34 | H2: 3 | I2: 99 | J2: 316
A3: 8 | B3: Student 1 | C3: 42 | D3: 79 | E3: 81 | F3: 85 | G3: 7 | H3: 72 | I3: 94 | J3: 460

Sheet Sheet4
A1: First Name | B1: Last Name | C1: Address | D1: City State | E1: ZIP | F1: Date of Birth
A2: Stephen | B2: Silva | C2: 7759 Johnson Ave. | D2: Glencoe,IL | E2: 60022 | F2: 2.9.1941
A3: John | B3: Lloyd | C3: 3842 Harrison St. | D3: Saddle River,NJ | E3: 7458 | F3: 3.11.1974
A4: Timothy | B4: Park | C4: 8001 Gore St. | D4: The Plains,VA | E4: 20198 | F4: 1.16.1955
A5: Michael | B5: Molina | C5: 7217 Lincoln Lane | D5: San Francisco,CA | E5: 94111 | F5: 3.2.1909
A6: Scott | B6: McDowell | C6: 6436 Taft St. | D6: Weston,CT | E6: 6883 | F6: 5.3.1932
A7: Randy | B7: Nixon | C7: 550 Polk Ave. | D7: Hinsdale,IL | E7: 60521 | F7: 1.8.1983
A8: Leonard | B8: Figueroa | C8: 8028 Wallace Ave. | D8: Belair Beach,FL | E8: 33786 | F8: 5.24.1909
A9: Robin | B9: Hutchinson | C9: 2247 Grant Ave. | D9: Rumson,NJ | E9: 7760 | F9: 12.27.1969
A10: Shira | B10: Nelson | C10: 5800 Humphrey Blvd. | D10: Franklin Lakes,NJ | E10: 7417 | F10: 1.6.1975
A11: Robert | B11: Daniel | C11: 4915 Adams Ct. | D11: Sherborn,MA | E11: 1770 | F11: 2.23.1965
A12: Brenda | B12: Barnett | C12: 887 Harrison St. | D12: Westport,CT | E12: 6880 | F12: 10.27.1945
A13: Jon | B13: Gregory | C13: 4247 Hoover Ct. | D13: Fort Worth,TX | E13: 76102 | F13: 12.15.1909
A14: Jan | B14: Ramos | C14: 6136 Harrison Ct. | D14: Portola Valley,CA | E14: 94028 | F14: 7.27.1959

Sheet Sheet6
A1: Product ID | B1: Product Name | C1: Category | D1: Region | E1: Salesperson | F1: Units Sold | G1: Unit Price | H1: Sale Value | I1: Month | M1: Product ID | N1: P001 | O1: P002 | P1: P003 | Q1: P004 | R1: P005 | S1: P006 | T1: P007 | U1: P008
A2: P001 | B2: Laptop | C2: Electronics | D2: North | E2: Alice | F2: 10 | G2: 600 | H2: =PRODUCT(F2,G2) -> 6000 | I2: January | M2: Product Name | N2: Laptop | O2: Mobile | P2: Chair | Q2: Table | R2: Laptop | S2: Sofa | T2: Mobile | U2: Table
A3: P002 | B3: Mobile | C3: Electronics | D3: South | E3: Bob | F3: 15 | G3: 400 | H3: =PRODUCT(F3,G3) -> 6000 | I3: January | M3: Category | N3: Electronics | O3: Electronics | P3: Furniture | Q3: Furniture | R3: Electronics | S3: Furniture | T3: Electronics | U3: Furniture
A4: P003 | B4: Chair | C4: Furniture | D4: East | E4: Charlie | F4: 20 | G4: 100 | H4: =PRODUCT(F4,G4) -> 2000 | I4: February | M4: Region | N4: North | O4: South | P4: East | Q4: West | R4: North | S4: South | T4: East | U4: West
A5: P004 | B5: Table | C5: Furniture | D5: West | E5: Alice | F5: 12 | G5: 200 | H5: =PRODUCT(F5,G5) -> 2400 | I5: February | M5: Salesperson | N5: Alice | O5: Bob | P5: Charlie | Q5: Alice | R5: Bob | S5: Charlie | T5: Alice | U5: Bob
A6: P005 | B6: Laptop | C6: Electronics | D6: North | E6: Bob | F6: 8 | G6: 600 | H6: =PRODUCT(F6,G6) -> 4800 | I6: March | M6: Units Sold | N6: 10 | O6: 15 | P6: 20 | Q6: 12 | R6: 8 | S6: 5 | T6: 18 | U6: 10
A7: P006 | B7: Sofa | C7: Furniture | D7: South | E7: Charlie | F7: 5 | G7: 500 | H7: =PRODUCT(F7,G7) -> 2500 | I7: March | M7: Unit Price | N7: 600 | O7: 400 | P7: 100 | Q7: 200 | R7: 600 | S7: 500 | T7: 400 | U7: 200
A8: P007 | B8: Mobile | C8: Electronics | D8: East | E8: Alice | F8: 18 | G8: 400 | H8: =PRODUCT(F8,G8) -> 7200 | I8: April | M8: Sale Value | N8: =PRODUCT(N6,N7) -> 6000 | O8: =PRODUCT(O6,O7) -> 6000 | P8: =PRODUCT(P6,P7) -> 2000 | Q8: =PRODUCT(Q6,Q7) -> 2400 | R8: =PRODUCT(R6,R7) -> 4800 | S8: =PRODUCT(S6,S7) -> 2500 | T8: =PRODUCT(T6,T7) -> 7200 | U8: =PRODUCT(U6,U7) -> 2000
A9: P008 | B9: Table | C9: Furniture | D9: West | E9: Bob | F9: 10 | G9: 200 | H9: =PRODUCT(F9,G9) -> 2000 | I9: May | M9: Month | N9: January | O9: January | P9: February | Q9: February | R9: March | S9: March | T9: April | U9: May
A16: Vertical Data
A17: Product ID | B17: Product Name | C17: Category | D17: Region | E17: Salesperson | F17: Units Sold | G17: Unit Price | H17: Sale Value | I17: Month
A18: P001 | B18: Laptop | C18: Electronics | D18: North | E18: Alice | F18: 0.9 | G18: 600 | H18: =PRODUCT(F18,G18) -> 540 | I18: January
A19: P002 | B19: Mobile | C19: Electronics | D19: South | E19: Bob | F19: 0.7 | G19: 400 | H19: =PRODUCT(F19,G19) -> 280 | I19: January
A20: P003 | B20: Chair | C20: Furniture | D20: East | E20: Charlie | F20: 0.5 | G20: 100 | H20: =PRODUCT(F20,G20) -> 50 | I20: February
A21: P004 | B21: Table | C21: Furniture | D21: West | E21: Alice | F21: 0.6 | G21: 200 | H21: =PRODUCT(F21,G21) -> 120 | I21: February
A22: P005 | B22: Laptop | C22: Electronics | D22: North | E22: Bob | F22: 0.8 | G22: 600 | H22: =PRODUCT(F22,G22) -> 480 | I22: March
A23: P006 | B23: Sofa | C23: Furniture | D23: South | E23: Charlie | F23: 0.5 | G23: 500 | H23: =PRODUCT(F23,G23) -> 250 | I23: March
A24: P007 | B24: Mobile | C24: Electronics | D24: East | E24: Alice | F24: 1 | G24: 400 | H24: =PRODUCT(F24,G24) -> 400 | I24: April
A25: P008 | B25: Table | C25: Furniture | D25: West | E25: Bob | F25: 0.9 | G25: 200 | H25: =PRODUCT(F25,G25) -> 180 | I25: May
